haip/__init__.py
haip/template.py
haip_template-0.1.3.dist-info/LICENSE
haip_template-0.1.3.dist-info/METADATA
haip_template-0.1.3.dist-info/WHEEL
haip_template-0.1.3.dist-info/top_level.txt
haip_template-0.1.3.dist-info/RECORD
