Metadata-Version: 2.1
Name: haip-template
Version: 0.1.3
Summary: Jinja2 based template module.
Home-page: https://github.com/haipdev/template
Author: Reinhard Hainz
Author-email: reinhard.hainz@gmail.com
License: UNKNOWN
Platform: UNKNOWN
Classifier: Programming Language :: Python :: 3
Classifier: License :: OSI Approved :: MIT License
Classifier: Operating System :: OS Independent
Requires-Dist: haip-config (>=0.1.7)
Requires-Dist: jinja2 (>=2.10)
